pydrawise/__init__.py
pydrawise/_version.py
pydrawise/auth.py
pydrawise/base.py
pydrawise/client.py
pydrawise/const.py
pydrawise/exceptions.py
pydrawise/hybrid.py
pydrawise/hydrawise.graphql
pydrawise/legacy.py
pydrawise/py.typed
pydrawise/rest.py
pydrawise/schema.py
pydrawise/schema_utils.py
pydrawise-2025.9.0.dist-info/licenses/LICENSE
pydrawise-2025.9.0.dist-info/METADATA
pydrawise-2025.9.0.dist-info/WHEEL
pydrawise-2025.9.0.dist-info/top_level.txt
pydrawise-2025.9.0.dist-info/zip-safe
pydrawise-2025.9.0.dist-info/RECORD
