Metadata-Version: 2.4
Name: pydrawise
Version: 2025.9.0
Summary: Python API for interacting with Hydrawise sprinkler controllers.
Author-email: David Knowles <dknowles2@gmail.com>
License: Apache-2.0
Project-URL: Homepage, https://github.com/dknowles2/pydrawise
Project-URL: Source Code, https://github.com/dknowles2/pydrawise
Project-URL: Bug Reports, https://github.com/dknowles2/pydrawise/issues
Keywords: hydrawise,api,iot
Platform: any
Classifier: Programming Language :: Python :: 3.12
Classifier: Programming Language :: Python :: 3.11
Classifier: Topic :: Software Development :: Libraries :: Python Modules
Requires-Python: >=3.11
License-File: LICENSE
Requires-Dist: aiohttp
Requires-Dist: apischema
Requires-Dist: gql
Requires-Dist: graphql-core
Requires-Dist: requests
Dynamic: license-file
